weno4.py
weno4-1.1.1.dist-info/LICENSE
weno4-1.1.1.dist-info/METADATA
weno4-1.1.1.dist-info/WHEEL
weno4-1.1.1.dist-info/top_level.txt
weno4-1.1.1.dist-info/RECORD
