Metadata-Version: 2.1
Name: weno4
Version: 1.1.1
Summary: WENO-4 Interpolation implemented from Janett et al (2019)
Home-page: http://github.com/Goobley/Weno4Interpolation
Author: Chris Osborne
Author-email: c.osborne.1@research.gla.ac.uk
License: MIT
Platform: UNKNOWN
Requires-Python: >=3.6
Requires-Dist: numpy
Requires-Dist: numba
